[{"$\\tilde{\\theta}$": 4.999291896820068, "$\\hat{\\theta}$": 4.99929666519165, "$\\tilde{\\ell}(\\cdot)$": -1418335.25, "$\\hat{\\ell}(\\cdot)$": -1418321.875, "$\\tilde{\\pi}(\\cdot)$": -8.916106224060059, "$\\hat{\\pi}(\\cdot)$": -8.916125297546387, "$\\tilde{\\mathcal{J}}(\\cdot)$": 6.9077558517456055, "$\\hat{\\mathcal{J}}(\\cdot)$": 6.907755374908447, "$\\Delta \\ell(\\cdot)$": -13.375, "$\\Delta \\pi(\\cdot)$": 1.9073486328125e-05, "$\\Delta \\mathcal{J}(\\cdot)$": -4.76837158203125e-07, "$\\log(p(\\hat{y}_{n+1}|x_{n+1}, D))$": -13.374980926513672, "$p(\\hat{y}_{n+1}|x_{n+1}, D)$": 1.553529841658019e-06}, {"$\\tilde{\\theta}$": 4.999292373657227, "$\\hat{\\theta}$": 4.99929666519165, "$\\tilde{\\ell}(\\cdot)$": -1418334.25, "$\\hat{\\ell}(\\cdot)$": -1418321.875, "$\\tilde{\\pi}(\\cdot)$": -8.916108131408691, "$\\hat{\\pi}(\\cdot)$": -8.916125297546387, "$\\tilde{\\mathcal{J}}(\\cdot)$": 6.9077558517456055, "$\\hat{\\mathcal{J}}(\\cdot)$": 6.907755374908447, "$\\Delta \\ell(\\cdot)$": -12.375, "$\\Delta \\pi(\\cdot)$": 1.71661376953125e-05, "$\\Delta \\mathcal{J}(\\cdot)$": -4.76837158203125e-07, "$\\log(p(\\hat{y}_{n+1}|x_{n+1}, D))$": -12.374982833862305, "$p(\\hat{y}_{n+1}|x_{n+1}, D)$": 4.222923962515779e-06}, {"$\\tilde{\\theta}$": 4.999292373657227, "$\\hat{\\theta}$": 4.99929666519165, "$\\tilde{\\ell}(\\cdot)$": -1418333.375, "$\\hat{\\ell}(\\cdot)$": -1418321.875, "$\\tilde{\\pi}(\\cdot)$": -8.916108131408691, "$\\hat{\\pi}(\\cdot)$": -8.916125297546387, "$\\tilde{\\mathcal{J}}(\\cdot)$": 6.9077558517456055, "$\\hat{\\mathcal{J}}(\\cdot)$": 6.907755374908447, "$\\Delta \\ell(\\cdot)$": -11.5, "$\\Delta \\pi(\\cdot)$": 1.71661376953125e-05, "$\\Delta \\mathcal{J}(\\cdot)$": -4.76837158203125e-07, "$\\log(p(\\hat{y}_{n+1}|x_{n+1}, D))$": -11.499982833862305, "$p(\\hat{y}_{n+1}|x_{n+1}, D)$": 1.013026758300839e-05}, {"$\\tilde{\\theta}$": 4.999292850494385, "$\\hat{\\theta}$": 4.99929666519165, "$\\tilde{\\ell}(\\cdot)$": -1418332.375, "$\\hat{\\ell}(\\cdot)$": -1418321.875, "$\\tilde{\\pi}(\\cdot)$": -8.916110038757324, "$\\hat{\\pi}(\\cdot)$": -8.916125297546387, "$\\tilde{\\mathcal{J}}(\\cdot)$": 6.9077558517456055, "$\\hat{\\mathcal{J}}(\\cdot)$": 6.907755374908447, "$\\Delta \\ell(\\cdot)$": -10.5, "$\\Delta \\pi(\\cdot)$": 1.52587890625e-05, "$\\Delta \\mathcal{J}(\\cdot)$": -4.76837158203125e-07, "$\\log(p(\\hat{y}_{n+1}|x_{n+1}, D))$": -10.499984741210938, "$p(\\hat{y}_{n+1}|x_{n+1}, D)$": 2.753686931100674e-05}, {"$\\tilde{\\theta}$": 4.999292850494385, "$\\hat{\\theta}$": 4.99929666519165, "$\\tilde{\\ell}(\\cdot)$": -1418331.5, "$\\hat{\\ell}(\\cdot)$": -1418321.875, "$\\tilde{\\pi}(\\cdot)$": -8.916110038757324, "$\\hat{\\pi}(\\cdot)$": -8.916125297546387, "$\\tilde{\\mathcal{J}}(\\cdot)$": 6.9077558517456055, "$\\hat{\\mathcal{J}}(\\cdot)$": 6.907755374908447, "$\\Delta \\ell(\\cdot)$": -9.625, "$\\Delta \\pi(\\cdot)$": 1.52587890625e-05, "$\\Delta \\mathcal{J}(\\cdot)$": -4.76837158203125e-07, "$\\log(p(\\hat{y}_{n+1}|x_{n+1}, D))$": -9.624984741210938, "$p(\\hat{y}_{n+1}|x_{n+1}, D)$": 6.605751696042717e-05}, {"$\\tilde{\\theta}$": 4.999292850494385, "$\\hat{\\theta}$": 4.99929666519165, "$\\tilde{\\ell}(\\cdot)$": -1418330.75, "$\\hat{\\ell}(\\cdot)$": -1418321.875, "$\\tilde{\\pi}(\\cdot)$": -8.916110038757324, "$\\hat{\\pi}(\\cdot)$": -8.916125297546387, "$\\tilde{\\mathcal{J}}(\\cdot)$": 6.9077558517456055, "$\\hat{\\mathcal{J}}(\\cdot)$": 6.907755374908447, "$\\Delta \\ell(\\cdot)$": -8.875, "$\\Delta \\pi(\\cdot)$": 1.52587890625e-05, "$\\Delta \\mathcal{J}(\\cdot)$": -4.76837158203125e-07, "$\\log(p(\\hat{y}_{n+1}|x_{n+1}, D))$": -8.874984741210938, "$p(\\hat{y}_{n+1}|x_{n+1}, D)$": 0.00013984375982545316}, {"$\\tilde{\\theta}$": 4.999293327331543, "$\\hat{\\theta}$": 4.99929666519165, "$\\tilde{\\ell}(\\cdot)$": -1418329.875, "$\\hat{\\ell}(\\cdot)$": -1418321.875, "$\\tilde{\\pi}(\\cdot)$": -8.916111946105957, "$\\hat{\\pi}(\\cdot)$": -8.916125297546387, "$\\tilde{\\mathcal{J}}(\\cdot)$": 6.9077558517456055, "$\\hat{\\mathcal{J}}(\\cdot)$": 6.907755374908447, "$\\Delta \\ell(\\cdot)$": -8.0, "$\\Delta \\pi(\\cdot)$": 1.33514404296875e-05, "$\\Delta \\mathcal{J}(\\cdot)$": -4.76837158203125e-07, "$\\log(p(\\hat{y}_{n+1}|x_{n+1}, D))$": -7.9999871253967285, "$p(\\hat{y}_{n+1}|x_{n+1}, D)$": 0.00033546696067787707}, {"$\\tilde{\\theta}$": 4.999293327331543, "$\\hat{\\theta}$": 4.99929666519165, "$\\tilde{\\ell}(\\cdot)$": -1418329.125, "$\\hat{\\ell}(\\cdot)$": -1418321.875, "$\\tilde{\\pi}(\\cdot)$": -8.916111946105957, "$\\hat{\\pi}(\\cdot)$": -8.916125297546387, "$\\tilde{\\mathcal{J}}(\\cdot)$": 6.9077558517456055, "$\\hat{\\mathcal{J}}(\\cdot)$": 6.907755374908447, "$\\Delta \\ell(\\cdot)$": -7.25, "$\\Delta \\pi(\\cdot)$": 1.33514404296875e-05, "$\\Delta \\mathcal{J}(\\cdot)$": -4.76837158203125e-07, "$\\log(p(\\hat{y}_{n+1}|x_{n+1}, D))$": -7.2499871253967285, "$p(\\hat{y}_{n+1}|x_{n+1}, D)$": 0.000710183521732688}, {"$\\tilde{\\theta}$": 4.999293804168701, "$\\hat{\\theta}$": 4.99929666519165, "$\\tilde{\\ell}(\\cdot)$": -1418328.5, "$\\hat{\\ell}(\\cdot)$": -1418321.875, "$\\tilde{\\pi}(\\cdot)$": -8.91611385345459, "$\\hat{\\pi}(\\cdot)$": -8.916125297546387, "$\\tilde{\\mathcal{J}}(\\cdot)$": 6.9077558517456055, "$\\hat{\\mathcal{J}}(\\cdot)$": 6.907755374908447, "$\\Delta \\ell(\\cdot)$": -6.625, "$\\Delta \\pi(\\cdot)$": 1.1444091796875e-05, "$\\Delta \\mathcal{J}(\\cdot)$": -4.76837158203125e-07, "$\\log(p(\\hat{y}_{n+1}|x_{n+1}, D))$": -6.624989032745361, "$p(\\hat{y}_{n+1}|x_{n+1}, D)$": 0.0013267949689179659}, {"$\\tilde{\\theta}$": 4.999293804168701, "$\\hat{\\theta}$": 4.99929666519165, "$\\tilde{\\ell}(\\cdot)$": -1418327.75, "$\\hat{\\ell}(\\cdot)$": -1418321.875, "$\\tilde{\\pi}(\\cdot)$": -8.91611385345459, "$\\hat{\\pi}(\\cdot)$": -8.916125297546387, "$\\tilde{\\mathcal{J}}(\\cdot)$": 6.9077558517456055, "$\\hat{\\mathcal{J}}(\\cdot)$": 6.907755374908447, "$\\Delta \\ell(\\cdot)$": -5.875, "$\\Delta \\pi(\\cdot)$": 1.1444091796875e-05, "$\\Delta \\mathcal{J}(\\cdot)$": -4.76837158203125e-07, "$\\log(p(\\hat{y}_{n+1}|x_{n+1}, D))$": -5.874989032745361, "$p(\\hat{y}_{n+1}|x_{n+1}, D)$": 0.0028088248800486326}, {"$\\tilde{\\theta}$": 4.999294281005859, "$\\hat{\\theta}$": 4.99929666519165, "$\\tilde{\\ell}(\\cdot)$": -1418327.125, "$\\hat{\\ell}(\\cdot)$": -1418321.875, "$\\tilde{\\pi}(\\cdot)$": -8.916115760803223, "$\\hat{\\pi}(\\cdot)$": -8.916125297546387, "$\\tilde{\\mathcal{J}}(\\cdot)$": 6.9077558517456055, "$\\hat{\\mathcal{J}}(\\cdot)$": 6.907755374908447, "$\\Delta \\ell(\\cdot)$": -5.25, "$\\Delta \\pi(\\cdot)$": 9.5367431640625e-06, "$\\Delta \\mathcal{J}(\\cdot)$": -4.76837158203125e-07, "$\\log(p(\\hat{y}_{n+1}|x_{n+1}, D))$": -5.249990940093994, "$p(\\hat{y}_{n+1}|x_{n+1}, D)$": 0.005247565917670727}, {"$\\tilde{\\theta}$": 4.999294281005859, "$\\hat{\\theta}$": 4.99929666519165, "$\\tilde{\\ell}(\\cdot)$": -1418326.625, "$\\hat{\\ell}(\\cdot)$": -1418321.875, "$\\tilde{\\pi}(\\cdot)$": -8.916115760803223, "$\\hat{\\pi}(\\cdot)$": -8.916125297546387, "$\\tilde{\\mathcal{J}}(\\cdot)$": 6.9077558517456055, "$\\hat{\\mathcal{J}}(\\cdot)$": 6.907755374908447, "$\\Delta \\ell(\\cdot)$": -4.75, "$\\Delta \\pi(\\cdot)$": 9.5367431640625e-06, "$\\Delta \\mathcal{J}(\\cdot)$": -4.76837158203125e-07, "$\\log(p(\\hat{y}_{n+1}|x_{n+1}, D))$": -4.749990940093994, "$p(\\hat{y}_{n+1}|x_{n+1}, D)$": 0.008651773445308208}, {"$\\tilde{\\theta}$": 4.999294281005859, "$\\hat{\\theta}$": 4.99929666519165, "$\\tilde{\\ell}(\\cdot)$": -1418326.0, "$\\hat{\\ell}(\\cdot)$": -1418321.875, "$\\tilde{\\pi}(\\cdot)$": -8.916115760803223, "$\\hat{\\pi}(\\cdot)$": -8.916125297546387, "$\\tilde{\\mathcal{J}}(\\cdot)$": 6.9077558517456055, "$\\hat{\\mathcal{J}}(\\cdot)$": 6.907755374908447, "$\\Delta \\ell(\\cdot)$": -4.125, "$\\Delta \\pi(\\cdot)$": 9.5367431640625e-06, "$\\Delta \\mathcal{J}(\\cdot)$": -4.76837158203125e-07, "$\\log(p(\\hat{y}_{n+1}|x_{n+1}, D))$": -4.124990940093994, "$p(\\hat{y}_{n+1}|x_{n+1}, D)$": 0.016163641586899757}, {"$\\tilde{\\theta}$": 4.999294757843018, "$\\hat{\\theta}$": 4.99929666519165, "$\\tilde{\\ell}(\\cdot)$": -1418325.5, "$\\hat{\\ell}(\\cdot)$": -1418321.875, "$\\tilde{\\pi}(\\cdot)$": -8.916117668151855, "$\\hat{\\pi}(\\cdot)$": -8.916125297546387, "$\\tilde{\\mathcal{J}}(\\cdot)$": 6.9077558517456055, "$\\hat{\\mathcal{J}}(\\cdot)$": 6.907755374908447, "$\\Delta \\ell(\\cdot)$": -3.625, "$\\Delta \\pi(\\cdot)$": 7.62939453125e-06, "$\\Delta \\mathcal{J}(\\cdot)$": -4.76837158203125e-07, "$\\log(p(\\hat{y}_{n+1}|x_{n+1}, D))$": -3.624992847442627, "$p(\\hat{y}_{n+1}|x_{n+1}, D)$": 0.026649288833141327}, {"$\\tilde{\\theta}$": 4.999294757843018, "$\\hat{\\theta}$": 4.99929666519165, "$\\tilde{\\ell}(\\cdot)$": -1418325.125, "$\\hat{\\ell}(\\cdot)$": -1418321.875, "$\\tilde{\\pi}(\\cdot)$": -8.916117668151855, "$\\hat{\\pi}(\\cdot)$": -8.916125297546387, "$\\tilde{\\mathcal{J}}(\\cdot)$": 6.9077558517456055, "$\\hat{\\mathcal{J}}(\\cdot)$": 6.907755374908447, "$\\Delta \\ell(\\cdot)$": -3.25, "$\\Delta \\pi(\\cdot)$": 7.62939453125e-06, "$\\Delta \\mathcal{J}(\\cdot)$": -4.76837158203125e-07, "$\\log(p(\\hat{y}_{n+1}|x_{n+1}, D))$": -3.249992847442627, "$p(\\hat{y}_{n+1}|x_{n+1}, D)$": 0.038774486631155014}, {"$\\tilde{\\theta}$": 4.999295234680176, "$\\hat{\\theta}$": 4.99929666519165, "$\\tilde{\\ell}(\\cdot)$": -1418324.625, "$\\hat{\\ell}(\\cdot)$": -1418321.875, "$\\tilde{\\pi}(\\cdot)$": -8.916119575500488, "$\\hat{\\pi}(\\cdot)$": -8.916125297546387, "$\\tilde{\\mathcal{J}}(\\cdot)$": 6.9077558517456055, "$\\hat{\\mathcal{J}}(\\cdot)$": 6.907755374908447, "$\\Delta \\ell(\\cdot)$": -2.75, "$\\Delta \\pi(\\cdot)$": 5.7220458984375e-06, "$\\Delta \\mathcal{J}(\\cdot)$": -4.76837158203125e-07, "$\\log(p(\\hat{y}_{n+1}|x_{n+1}, D))$": -2.7499947547912598, "$p(\\hat{y}_{n+1}|x_{n+1}, D)$": 0.06392819434404373}, {"$\\tilde{\\theta}$": 4.999295234680176, "$\\hat{\\theta}$": 4.99929666519165, "$\\tilde{\\ell}(\\cdot)$": -1418324.25, "$\\hat{\\ell}(\\cdot)$": -1418321.875, "$\\tilde{\\pi}(\\cdot)$": -8.916119575500488, "$\\hat{\\pi}(\\cdot)$": -8.916125297546387, "$\\tilde{\\mathcal{J}}(\\cdot)$": 6.9077558517456055, "$\\hat{\\mathcal{J}}(\\cdot)$": 6.907755374908447, "$\\Delta \\ell(\\cdot)$": -2.375, "$\\Delta \\pi(\\cdot)$": 5.7220458984375e-06, "$\\Delta \\mathcal{J}(\\cdot)$": -4.76837158203125e-07, "$\\log(p(\\hat{y}_{n+1}|x_{n+1}, D))$": -2.3749947547912598, "$p(\\hat{y}_{n+1}|x_{n+1}, D)$": 0.09301497787237167}, {"$\\tilde{\\theta}$": 4.999295234680176, "$\\hat{\\theta}$": 4.99929666519165, "$\\tilde{\\ell}(\\cdot)$": -1418324.0, "$\\hat{\\ell}(\\cdot)$": -1418321.875, "$\\tilde{\\pi}(\\cdot)$": -8.916119575500488, "$\\hat{\\pi}(\\cdot)$": -8.916125297546387, "$\\tilde{\\mathcal{J}}(\\cdot)$": 6.9077558517456055, "$\\hat{\\mathcal{J}}(\\cdot)$": 6.907755374908447, "$\\Delta \\ell(\\cdot)$": -2.125, "$\\Delta \\pi(\\cdot)$": 5.7220458984375e-06, "$\\Delta \\mathcal{J}(\\cdot)$": -4.76837158203125e-07, "$\\log(p(\\hat{y}_{n+1}|x_{n+1}, D))$": -2.1249947547912598, "$p(\\hat{y}_{n+1}|x_{n+1}, D)$": 0.11943359673023224}, {"$\\tilde{\\theta}$": 4.999295711517334, "$\\hat{\\theta}$": 4.99929666519165, "$\\tilde{\\ell}(\\cdot)$": -1418323.625, "$\\hat{\\ell}(\\cdot)$": -1418321.875, "$\\tilde{\\pi}(\\cdot)$": -8.916121482849121, "$\\hat{\\pi}(\\cdot)$": -8.916125297546387, "$\\tilde{\\mathcal{J}}(\\cdot)$": 6.9077558517456055, "$\\hat{\\mathcal{J}}(\\cdot)$": 6.907755374908447, "$\\Delta \\ell(\\cdot)$": -1.75, "$\\Delta \\pi(\\cdot)$": 3.814697265625e-06, "$\\Delta \\mathcal{J}(\\cdot)$": -4.76837158203125e-07, "$\\log(p(\\hat{y}_{n+1}|x_{n+1}, D))$": -1.7499966621398926, "$p(\\hat{y}_{n+1}|x_{n+1}, D)$": 0.17377452552318573}, {"$\\tilde{\\theta}$": 4.999295711517334, "$\\hat{\\theta}$": 4.99929666519165, "$\\tilde{\\ell}(\\cdot)$": -1418323.375, "$\\hat{\\ell}(\\cdot)$": -1418321.875, "$\\tilde{\\pi}(\\cdot)$": -8.916121482849121, "$\\hat{\\pi}(\\cdot)$": -8.916125297546387, "$\\tilde{\\mathcal{J}}(\\cdot)$": 6.9077558517456055, "$\\hat{\\mathcal{J}}(\\cdot)$": 6.907755374908447, "$\\Delta \\ell(\\cdot)$": -1.5, "$\\Delta \\pi(\\cdot)$": 3.814697265625e-06, "$\\Delta \\mathcal{J}(\\cdot)$": -4.76837158203125e-07, "$\\log(p(\\hat{y}_{n+1}|x_{n+1}, D))$": -1.4999966621398926, "$p(\\hat{y}_{n+1}|x_{n+1}, D)$": 0.22313091158866882}, {"$\\tilde{\\theta}$": 4.999296188354492, "$\\hat{\\theta}$": 4.99929666519165, "$\\tilde{\\ell}(\\cdot)$": -1418323.25, "$\\hat{\\ell}(\\cdot)$": -1418321.875, "$\\tilde{\\pi}(\\cdot)$": -8.916123390197754, "$\\hat{\\pi}(\\cdot)$": -8.916125297546387, "$\\tilde{\\mathcal{J}}(\\cdot)$": 6.9077558517456055, "$\\hat{\\mathcal{J}}(\\cdot)$": 6.907755374908447, "$\\Delta \\ell(\\cdot)$": -1.375, "$\\Delta \\pi(\\cdot)$": 1.9073486328125e-06, "$\\Delta \\mathcal{J}(\\cdot)$": -4.76837158203125e-07, "$\\log(p(\\hat{y}_{n+1}|x_{n+1}, D))$": -1.3749985694885254, "$p(\\hat{y}_{n+1}|x_{n+1}, D)$": 0.25283995270729065}, {"$\\tilde{\\theta}$": 4.999296188354492, "$\\hat{\\theta}$": 4.99929666519165, "$\\tilde{\\ell}(\\cdot)$": -1418323.0, "$\\hat{\\ell}(\\cdot)$": -1418321.875, "$\\tilde{\\pi}(\\cdot)$": -8.916123390197754, "$\\hat{\\pi}(\\cdot)$": -8.916125297546387, "$\\tilde{\\mathcal{J}}(\\cdot)$": 6.9077558517456055, "$\\hat{\\mathcal{J}}(\\cdot)$": 6.907755374908447, "$\\Delta \\ell(\\cdot)$": -1.125, "$\\Delta \\pi(\\cdot)$": 1.9073486328125e-06, "$\\Delta \\mathcal{J}(\\cdot)$": -4.76837158203125e-07, "$\\log(p(\\hat{y}_{n+1}|x_{n+1}, D))$": -1.1249985694885254, "$p(\\hat{y}_{n+1}|x_{n+1}, D)$": 0.32465294003486633}, {"$\\tilde{\\theta}$": 4.999296188354492, "$\\hat{\\theta}$": 4.99929666519165, "$\\tilde{\\ell}(\\cdot)$": -1418322.875, "$\\hat{\\ell}(\\cdot)$": -1418321.875, "$\\tilde{\\pi}(\\cdot)$": -8.916123390197754, "$\\hat{\\pi}(\\cdot)$": -8.916125297546387, "$\\tilde{\\mathcal{J}}(\\cdot)$": 6.9077558517456055, "$\\hat{\\mathcal{J}}(\\cdot)$": 6.907755374908447, "$\\Delta \\ell(\\cdot)$": -1.0, "$\\Delta \\pi(\\cdot)$": 1.9073486328125e-06, "$\\Delta \\mathcal{J}(\\cdot)$": -4.76837158203125e-07, "$\\log(p(\\hat{y}_{n+1}|x_{n+1}, D))$": -0.9999985694885254, "$p(\\hat{y}_{n+1}|x_{n+1}, D)$": 0.3678799569606781}, {"$\\tilde{\\theta}$": 4.99929666519165, "$\\hat{\\theta}$": 4.99929666519165, "$\\tilde{\\ell}(\\cdot)$": -1418322.875, "$\\hat{\\ell}(\\cdot)$": -1418321.875, "$\\tilde{\\pi}(\\cdot)$": -8.916125297546387, "$\\hat{\\pi}(\\cdot)$": -8.916125297546387, "$\\tilde{\\mathcal{J}}(\\cdot)$": 6.9077558517456055, "$\\hat{\\mathcal{J}}(\\cdot)$": 6.907755374908447, "$\\Delta \\ell(\\cdot)$": -1.0, "$\\Delta \\pi(\\cdot)$": 0.0, "$\\Delta \\mathcal{J}(\\cdot)$": -4.76837158203125e-07, "$\\log(p(\\hat{y}_{n+1}|x_{n+1}, D))$": -1.0000004768371582, "$p(\\hat{y}_{n+1}|x_{n+1}, D)$": 0.3678792715072632}, {"$\\tilde{\\theta}$": 4.99929666519165, "$\\hat{\\theta}$": 4.99929666519165, "$\\tilde{\\ell}(\\cdot)$": -1418322.75, "$\\hat{\\ell}(\\cdot)$": -1418321.875, "$\\tilde{\\pi}(\\cdot)$": -8.916125297546387, "$\\hat{\\pi}(\\cdot)$": -8.916125297546387, "$\\tilde{\\mathcal{J}}(\\cdot)$": 6.9077558517456055, "$\\hat{\\mathcal{J}}(\\cdot)$": 6.907755374908447, "$\\Delta \\ell(\\cdot)$": -0.875, "$\\Delta \\pi(\\cdot)$": 0.0, "$\\Delta \\mathcal{J}(\\cdot)$": -4.76837158203125e-07, "$\\log(p(\\hat{y}_{n+1}|x_{n+1}, D))$": -0.8750004768371582, "$p(\\hat{y}_{n+1}|x_{n+1}, D)$": 0.4168618321418762}, {"$\\tilde{\\theta}$": 4.999297142028809, "$\\hat{\\theta}$": 4.99929666519165, "$\\tilde{\\ell}(\\cdot)$": -1418322.75, "$\\hat{\\ell}(\\cdot)$": -1418321.875, "$\\tilde{\\pi}(\\cdot)$": -8.91612720489502, "$\\hat{\\pi}(\\cdot)$": -8.916125297546387, "$\\tilde{\\mathcal{J}}(\\cdot)$": 6.9077558517456055, "$\\hat{\\mathcal{J}}(\\cdot)$": 6.907755374908447, "$\\Delta \\ell(\\cdot)$": -0.875, "$\\Delta \\pi(\\cdot)$": -1.9073486328125e-06, "$\\Delta \\mathcal{J}(\\cdot)$": -4.76837158203125e-07, "$\\log(p(\\hat{y}_{n+1}|x_{n+1}, D))$": -0.875002384185791, "$p(\\hat{y}_{n+1}|x_{n+1}, D)$": 0.41686102747917175}, {"$\\tilde{\\theta}$": 4.999297142028809, "$\\hat{\\theta}$": 4.99929666519165, "$\\tilde{\\ell}(\\cdot)$": -1418322.875, "$\\hat{\\ell}(\\cdot)$": -1418321.875, "$\\tilde{\\pi}(\\cdot)$": -8.91612720489502, "$\\hat{\\pi}(\\cdot)$": -8.916125297546387, "$\\tilde{\\mathcal{J}}(\\cdot)$": 6.9077558517456055, "$\\hat{\\mathcal{J}}(\\cdot)$": 6.907755374908447, "$\\Delta \\ell(\\cdot)$": -1.0, "$\\Delta \\pi(\\cdot)$": -1.9073486328125e-06, "$\\Delta \\mathcal{J}(\\cdot)$": -4.76837158203125e-07, "$\\log(p(\\hat{y}_{n+1}|x_{n+1}, D))$": -1.000002384185791, "$p(\\hat{y}_{n+1}|x_{n+1}, D)$": 0.3678785562515259}, {"$\\tilde{\\theta}$": 4.999297142028809, "$\\hat{\\theta}$": 4.99929666519165, "$\\tilde{\\ell}(\\cdot)$": -1418322.875, "$\\hat{\\ell}(\\cdot)$": -1418321.875, "$\\tilde{\\pi}(\\cdot)$": -8.91612720489502, "$\\hat{\\pi}(\\cdot)$": -8.916125297546387, "$\\tilde{\\mathcal{J}}(\\cdot)$": 6.9077558517456055, "$\\hat{\\mathcal{J}}(\\cdot)$": 6.907755374908447, "$\\Delta \\ell(\\cdot)$": -1.0, "$\\Delta \\pi(\\cdot)$": -1.9073486328125e-06, "$\\Delta \\mathcal{J}(\\cdot)$": -4.76837158203125e-07, "$\\log(p(\\hat{y}_{n+1}|x_{n+1}, D))$": -1.000002384185791, "$p(\\hat{y}_{n+1}|x_{n+1}, D)$": 0.3678785562515259}, {"$\\tilde{\\theta}$": 4.999298095703125, "$\\hat{\\theta}$": 4.99929666519165, "$\\tilde{\\ell}(\\cdot)$": -1418322.875, "$\\hat{\\ell}(\\cdot)$": -1418321.875, "$\\tilde{\\pi}(\\cdot)$": -8.916131019592285, "$\\hat{\\pi}(\\cdot)$": -8.916125297546387, "$\\tilde{\\mathcal{J}}(\\cdot)$": 6.9077558517456055, "$\\hat{\\mathcal{J}}(\\cdot)$": 6.907755374908447, "$\\Delta \\ell(\\cdot)$": -1.0, "$\\Delta \\pi(\\cdot)$": -5.7220458984375e-06, "$\\Delta \\mathcal{J}(\\cdot)$": -4.76837158203125e-07, "$\\log(p(\\hat{y}_{n+1}|x_{n+1}, D))$": -1.0000061988830566, "$p(\\hat{y}_{n+1}|x_{n+1}, D)$": 0.36787715554237366}, {"$\\tilde{\\theta}$": 4.999298095703125, "$\\hat{\\theta}$": 4.99929666519165, "$\\tilde{\\ell}(\\cdot)$": -1418323.125, "$\\hat{\\ell}(\\cdot)$": -1418321.875, "$\\tilde{\\pi}(\\cdot)$": -8.916131019592285, "$\\hat{\\pi}(\\cdot)$": -8.916125297546387, "$\\tilde{\\mathcal{J}}(\\cdot)$": 6.9077558517456055, "$\\hat{\\mathcal{J}}(\\cdot)$": 6.907755374908447, "$\\Delta \\ell(\\cdot)$": -1.25, "$\\Delta \\pi(\\cdot)$": -5.7220458984375e-06, "$\\Delta \\mathcal{J}(\\cdot)$": -4.76837158203125e-07, "$\\log(p(\\hat{y}_{n+1}|x_{n+1}, D))$": -1.2500061988830566, "$p(\\hat{y}_{n+1}|x_{n+1}, D)$": 0.28650301694869995}, {"$\\tilde{\\theta}$": 4.999298572540283, "$\\hat{\\theta}$": 4.99929666519165, "$\\tilde{\\ell}(\\cdot)$": -1418323.375, "$\\hat{\\ell}(\\cdot)$": -1418321.875, "$\\tilde{\\pi}(\\cdot)$": -8.916132926940918, "$\\hat{\\pi}(\\cdot)$": -8.916125297546387, "$\\tilde{\\mathcal{J}}(\\cdot)$": 6.9077558517456055, "$\\hat{\\mathcal{J}}(\\cdot)$": 6.907755374908447, "$\\Delta \\ell(\\cdot)$": -1.5, "$\\Delta \\pi(\\cdot)$": -7.62939453125e-06, "$\\Delta \\mathcal{J}(\\cdot)$": -4.76837158203125e-07, "$\\log(p(\\hat{y}_{n+1}|x_{n+1}, D))$": -1.5000081062316895, "$p(\\hat{y}_{n+1}|x_{n+1}, D)$": 0.22312834858894348}, {"$\\tilde{\\theta}$": 4.999298572540283, "$\\hat{\\theta}$": 4.99929666519165, "$\\tilde{\\ell}(\\cdot)$": -1418323.625, "$\\hat{\\ell}(\\cdot)$": -1418321.875, "$\\tilde{\\pi}(\\cdot)$": -8.916132926940918, "$\\hat{\\pi}(\\cdot)$": -8.916125297546387, "$\\tilde{\\mathcal{J}}(\\cdot)$": 6.9077558517456055, "$\\hat{\\mathcal{J}}(\\cdot)$": 6.907755374908447, "$\\Delta \\ell(\\cdot)$": -1.75, "$\\Delta \\pi(\\cdot)$": -7.62939453125e-06, "$\\Delta \\mathcal{J}(\\cdot)$": -4.76837158203125e-07, "$\\log(p(\\hat{y}_{n+1}|x_{n+1}, D))$": -1.7500081062316895, "$p(\\hat{y}_{n+1}|x_{n+1}, D)$": 0.17377252876758575}, {"$\\tilde{\\theta}$": 4.999298572540283, "$\\hat{\\theta}$": 4.99929666519165, "$\\tilde{\\ell}(\\cdot)$": -1418324.0, "$\\hat{\\ell}(\\cdot)$": -1418321.875, "$\\tilde{\\pi}(\\cdot)$": -8.916132926940918, "$\\hat{\\pi}(\\cdot)$": -8.916125297546387, "$\\tilde{\\mathcal{J}}(\\cdot)$": 6.9077558517456055, "$\\hat{\\mathcal{J}}(\\cdot)$": 6.907755374908447, "$\\Delta \\ell(\\cdot)$": -2.125, "$\\Delta \\pi(\\cdot)$": -7.62939453125e-06, "$\\Delta \\mathcal{J}(\\cdot)$": -4.76837158203125e-07, "$\\log(p(\\hat{y}_{n+1}|x_{n+1}, D))$": -2.1250081062316895, "$p(\\hat{y}_{n+1}|x_{n+1}, D)$": 0.1194320023059845}, {"$\\tilde{\\theta}$": 4.999299049377441, "$\\hat{\\theta}$": 4.99929666519165, "$\\tilde{\\ell}(\\cdot)$": -1418324.25, "$\\hat{\\ell}(\\cdot)$": -1418321.875, "$\\tilde{\\pi}(\\cdot)$": -8.91613483428955, "$\\hat{\\pi}(\\cdot)$": -8.916125297546387, "$\\tilde{\\mathcal{J}}(\\cdot)$": 6.9077558517456055, "$\\hat{\\mathcal{J}}(\\cdot)$": 6.907755374908447, "$\\Delta \\ell(\\cdot)$": -2.375, "$\\Delta \\pi(\\cdot)$": -9.5367431640625e-06, "$\\Delta \\mathcal{J}(\\cdot)$": -4.76837158203125e-07, "$\\log(p(\\hat{y}_{n+1}|x_{n+1}, D))$": -2.3750100135803223, "$p(\\hat{y}_{n+1}|x_{n+1}, D)$": 0.09301355481147766}, {"$\\tilde{\\theta}$": 4.999299049377441, "$\\hat{\\theta}$": 4.99929666519165, "$\\tilde{\\ell}(\\cdot)$": -1418324.625, "$\\hat{\\ell}(\\cdot)$": -1418321.875, "$\\tilde{\\pi}(\\cdot)$": -8.91613483428955, "$\\hat{\\pi}(\\cdot)$": -8.916125297546387, "$\\tilde{\\mathcal{J}}(\\cdot)$": 6.9077558517456055, "$\\hat{\\mathcal{J}}(\\cdot)$": 6.907755374908447, "$\\Delta \\ell(\\cdot)$": -2.75, "$\\Delta \\pi(\\cdot)$": -9.5367431640625e-06, "$\\Delta \\mathcal{J}(\\cdot)$": -4.76837158203125e-07, "$\\log(p(\\hat{y}_{n+1}|x_{n+1}, D))$": -2.7500100135803223, "$p(\\hat{y}_{n+1}|x_{n+1}, D)$": 0.06392721831798553}, {"$\\tilde{\\theta}$": 4.9992995262146, "$\\hat{\\theta}$": 4.99929666519165, "$\\tilde{\\ell}(\\cdot)$": -1418325.125, "$\\hat{\\ell}(\\cdot)$": -1418321.875, "$\\tilde{\\pi}(\\cdot)$": -8.916136741638184, "$\\hat{\\pi}(\\cdot)$": -8.916125297546387, "$\\tilde{\\mathcal{J}}(\\cdot)$": 6.9077558517456055, "$\\hat{\\mathcal{J}}(\\cdot)$": 6.907755374908447, "$\\Delta \\ell(\\cdot)$": -3.25, "$\\Delta \\pi(\\cdot)$": -1.1444091796875e-05, "$\\Delta \\mathcal{J}(\\cdot)$": -4.76837158203125e-07, "$\\log(p(\\hat{y}_{n+1}|x_{n+1}, D))$": -3.250011920928955, "$p(\\hat{y}_{n+1}|x_{n+1}, D)$": 0.03877374529838562}, {"$\\tilde{\\theta}$": 4.9992995262146, "$\\hat{\\theta}$": 4.99929666519165, "$\\tilde{\\ell}(\\cdot)$": -1418325.5, "$\\hat{\\ell}(\\cdot)$": -1418321.875, "$\\tilde{\\pi}(\\cdot)$": -8.916136741638184, "$\\hat{\\pi}(\\cdot)$": -8.916125297546387, "$\\tilde{\\mathcal{J}}(\\cdot)$": 6.9077558517456055, "$\\hat{\\mathcal{J}}(\\cdot)$": 6.907755374908447, "$\\Delta \\ell(\\cdot)$": -3.625, "$\\Delta \\pi(\\cdot)$": -1.1444091796875e-05, "$\\Delta \\mathcal{J}(\\cdot)$": -4.76837158203125e-07, "$\\log(p(\\hat{y}_{n+1}|x_{n+1}, D))$": -3.625011920928955, "$p(\\hat{y}_{n+1}|x_{n+1}, D)$": 0.026648780331015587}, {"$\\tilde{\\theta}$": 4.999300003051758, "$\\hat{\\theta}$": 4.99929666519165, "$\\tilde{\\ell}(\\cdot)$": -1418326.0, "$\\hat{\\ell}(\\cdot)$": -1418321.875, "$\\tilde{\\pi}(\\cdot)$": -8.916138648986816, "$\\hat{\\pi}(\\cdot)$": -8.916125297546387, "$\\tilde{\\mathcal{J}}(\\cdot)$": 6.9077558517456055, "$\\hat{\\mathcal{J}}(\\cdot)$": 6.907755374908447, "$\\Delta \\ell(\\cdot)$": -4.125, "$\\Delta \\pi(\\cdot)$": -1.33514404296875e-05, "$\\Delta \\mathcal{J}(\\cdot)$": -4.76837158203125e-07, "$\\log(p(\\hat{y}_{n+1}|x_{n+1}, D))$": -4.125013828277588, "$p(\\hat{y}_{n+1}|x_{n+1}, D)$": 0.01616327092051506}, {"$\\tilde{\\theta}$": 4.999300003051758, "$\\hat{\\theta}$": 4.99929666519165, "$\\tilde{\\ell}(\\cdot)$": -1418326.625, "$\\hat{\\ell}(\\cdot)$": -1418321.875, "$\\tilde{\\pi}(\\cdot)$": -8.916138648986816, "$\\hat{\\pi}(\\cdot)$": -8.916125297546387, "$\\tilde{\\mathcal{J}}(\\cdot)$": 6.9077558517456055, "$\\hat{\\mathcal{J}}(\\cdot)$": 6.907755374908447, "$\\Delta \\ell(\\cdot)$": -4.75, "$\\Delta \\pi(\\cdot)$": -1.33514404296875e-05, "$\\Delta \\mathcal{J}(\\cdot)$": -4.76837158203125e-07, "$\\log(p(\\hat{y}_{n+1}|x_{n+1}, D))$": -4.750013828277588, "$p(\\hat{y}_{n+1}|x_{n+1}, D)$": 0.008651575073599815}, {"$\\tilde{\\theta}$": 4.999300003051758, "$\\hat{\\theta}$": 4.99929666519165, "$\\tilde{\\ell}(\\cdot)$": -1418327.125, "$\\hat{\\ell}(\\cdot)$": -1418321.875, "$\\tilde{\\pi}(\\cdot)$": -8.916138648986816, "$\\hat{\\pi}(\\cdot)$": -8.916125297546387, "$\\tilde{\\mathcal{J}}(\\cdot)$": 6.9077558517456055, "$\\hat{\\mathcal{J}}(\\cdot)$": 6.907755374908447, "$\\Delta \\ell(\\cdot)$": -5.25, "$\\Delta \\pi(\\cdot)$": -1.33514404296875e-05, "$\\Delta \\mathcal{J}(\\cdot)$": -4.76837158203125e-07, "$\\log(p(\\hat{y}_{n+1}|x_{n+1}, D))$": -5.250013828277588, "$p(\\hat{y}_{n+1}|x_{n+1}, D)$": 0.005247445777058601}, {"$\\tilde{\\theta}$": 4.999300479888916, "$\\hat{\\theta}$": 4.99929666519165, "$\\tilde{\\ell}(\\cdot)$": -1418327.75, "$\\hat{\\ell}(\\cdot)$": -1418321.875, "$\\tilde{\\pi}(\\cdot)$": -8.91614055633545, "$\\hat{\\pi}(\\cdot)$": -8.916125297546387, "$\\tilde{\\mathcal{J}}(\\cdot)$": 6.9077558517456055, "$\\hat{\\mathcal{J}}(\\cdot)$": 6.907755374908447, "$\\Delta \\ell(\\cdot)$": -5.875, "$\\Delta \\pi(\\cdot)$": -1.52587890625e-05, "$\\Delta \\mathcal{J}(\\cdot)$": -4.76837158203125e-07, "$\\log(p(\\hat{y}_{n+1}|x_{n+1}, D))$": -5.875015735626221, "$p(\\hat{y}_{n+1}|x_{n+1}, D)$": 0.002808749908581376}, {"$\\tilde{\\theta}$": 4.999300479888916, "$\\hat{\\theta}$": 4.99929666519165, "$\\tilde{\\ell}(\\cdot)$": -1418328.5, "$\\hat{\\ell}(\\cdot)$": -1418321.875, "$\\tilde{\\pi}(\\cdot)$": -8.91614055633545, "$\\hat{\\pi}(\\cdot)$": -8.916125297546387, "$\\tilde{\\mathcal{J}}(\\cdot)$": 6.9077558517456055, "$\\hat{\\mathcal{J}}(\\cdot)$": 6.907755374908447, "$\\Delta \\ell(\\cdot)$": -6.625, "$\\Delta \\pi(\\cdot)$": -1.52587890625e-05, "$\\Delta \\mathcal{J}(\\cdot)$": -4.76837158203125e-07, "$\\log(p(\\hat{y}_{n+1}|x_{n+1}, D))$": -6.625015735626221, "$p(\\hat{y}_{n+1}|x_{n+1}, D)$": 0.0013267595786601305}, {"$\\tilde{\\theta}$": 4.999300956726074, "$\\hat{\\theta}$": 4.99929666519165, "$\\tilde{\\ell}(\\cdot)$": -1418329.125, "$\\hat{\\ell}(\\cdot)$": -1418321.875, "$\\tilde{\\pi}(\\cdot)$": -8.916142463684082, "$\\hat{\\pi}(\\cdot)$": -8.916125297546387, "$\\tilde{\\mathcal{J}}(\\cdot)$": 6.9077558517456055, "$\\hat{\\mathcal{J}}(\\cdot)$": 6.907755374908447, "$\\Delta \\ell(\\cdot)$": -7.25, "$\\Delta \\pi(\\cdot)$": -1.71661376953125e-05, "$\\Delta \\mathcal{J}(\\cdot)$": -4.76837158203125e-07, "$\\log(p(\\hat{y}_{n+1}|x_{n+1}, D))$": -7.2500176429748535, "$p(\\hat{y}_{n+1}|x_{n+1}, D)$": 0.0007101618684828281}, {"$\\tilde{\\theta}$": 4.999300956726074, "$\\hat{\\theta}$": 4.99929666519165, "$\\tilde{\\ell}(\\cdot)$": -1418329.875, "$\\hat{\\ell}(\\cdot)$": -1418321.875, "$\\tilde{\\pi}(\\cdot)$": -8.916142463684082, "$\\hat{\\pi}(\\cdot)$": -8.916125297546387, "$\\tilde{\\mathcal{J}}(\\cdot)$": 6.9077558517456055, "$\\hat{\\mathcal{J}}(\\cdot)$": 6.907755374908447, "$\\Delta \\ell(\\cdot)$": -8.0, "$\\Delta \\pi(\\cdot)$": -1.71661376953125e-05, "$\\Delta \\mathcal{J}(\\cdot)$": -4.76837158203125e-07, "$\\log(p(\\hat{y}_{n+1}|x_{n+1}, D))$": -8.000017166137695, "$p(\\hat{y}_{n+1}|x_{n+1}, D)$": 0.0003354568616487086}, {"$\\tilde{\\theta}$": 4.999300956726074, "$\\hat{\\theta}$": 4.99929666519165, "$\\tilde{\\ell}(\\cdot)$": -1418330.75, "$\\hat{\\ell}(\\cdot)$": -1418321.875, "$\\tilde{\\pi}(\\cdot)$": -8.916142463684082, "$\\hat{\\pi}(\\cdot)$": -8.916125297546387, "$\\tilde{\\mathcal{J}}(\\cdot)$": 6.9077558517456055, "$\\hat{\\mathcal{J}}(\\cdot)$": 6.907755374908447, "$\\Delta \\ell(\\cdot)$": -8.875, "$\\Delta \\pi(\\cdot)$": -1.71661376953125e-05, "$\\Delta \\mathcal{J}(\\cdot)$": -4.76837158203125e-07, "$\\log(p(\\hat{y}_{n+1}|x_{n+1}, D))$": -8.875017166137695, "$p(\\hat{y}_{n+1}|x_{n+1}, D)$": 0.00013983923417981714}, {"$\\tilde{\\theta}$": 4.999301433563232, "$\\hat{\\theta}$": 4.99929666519165, "$\\tilde{\\ell}(\\cdot)$": -1418331.5, "$\\hat{\\ell}(\\cdot)$": -1418321.875, "$\\tilde{\\pi}(\\cdot)$": -8.916144371032715, "$\\hat{\\pi}(\\cdot)$": -8.916125297546387, "$\\tilde{\\mathcal{J}}(\\cdot)$": 6.9077558517456055, "$\\hat{\\mathcal{J}}(\\cdot)$": 6.907755374908447, "$\\Delta \\ell(\\cdot)$": -9.625, "$\\Delta \\pi(\\cdot)$": -1.9073486328125e-05, "$\\Delta \\mathcal{J}(\\cdot)$": -4.76837158203125e-07, "$\\log(p(\\hat{y}_{n+1}|x_{n+1}, D))$": -9.625019073486328, "$p(\\hat{y}_{n+1}|x_{n+1}, D)$": 6.605524686165154e-05}, {"$\\tilde{\\theta}$": 4.999301433563232, "$\\hat{\\theta}$": 4.99929666519165, "$\\tilde{\\ell}(\\cdot)$": -1418332.375, "$\\hat{\\ell}(\\cdot)$": -1418321.875, "$\\tilde{\\pi}(\\cdot)$": -8.916144371032715, "$\\hat{\\pi}(\\cdot)$": -8.916125297546387, "$\\tilde{\\mathcal{J}}(\\cdot)$": 6.9077558517456055, "$\\hat{\\mathcal{J}}(\\cdot)$": 6.907755374908447, "$\\Delta \\ell(\\cdot)$": -10.5, "$\\Delta \\pi(\\cdot)$": -1.9073486328125e-05, "$\\Delta \\mathcal{J}(\\cdot)$": -4.76837158203125e-07, "$\\log(p(\\hat{y}_{n+1}|x_{n+1}, D))$": -10.500019073486328, "$p(\\hat{y}_{n+1}|x_{n+1}, D)$": 2.7535923436516896e-05}, {"$\\tilde{\\theta}$": 4.999301910400391, "$\\hat{\\theta}$": 4.99929666519165, "$\\tilde{\\ell}(\\cdot)$": -1418333.375, "$\\hat{\\ell}(\\cdot)$": -1418321.875, "$\\tilde{\\pi}(\\cdot)$": -8.916146278381348, "$\\hat{\\pi}(\\cdot)$": -8.916125297546387, "$\\tilde{\\mathcal{J}}(\\cdot)$": 6.9077558517456055, "$\\hat{\\mathcal{J}}(\\cdot)$": 6.907755374908447, "$\\Delta \\ell(\\cdot)$": -11.5, "$\\Delta \\pi(\\cdot)$": -2.09808349609375e-05, "$\\Delta \\mathcal{J}(\\cdot)$": -4.76837158203125e-07, "$\\log(p(\\hat{y}_{n+1}|x_{n+1}, D))$": -11.500020980834961, "$p(\\hat{y}_{n+1}|x_{n+1}, D)$": 1.0129881047760136e-05}, {"$\\tilde{\\theta}$": 4.999301910400391, "$\\hat{\\theta}$": 4.99929666519165, "$\\tilde{\\ell}(\\cdot)$": -1418334.25, "$\\hat{\\ell}(\\cdot)$": -1418321.875, "$\\tilde{\\pi}(\\cdot)$": -8.916146278381348, "$\\hat{\\pi}(\\cdot)$": -8.916125297546387, "$\\tilde{\\mathcal{J}}(\\cdot)$": 6.9077558517456055, "$\\hat{\\mathcal{J}}(\\cdot)$": 6.907755374908447, "$\\Delta \\ell(\\cdot)$": -12.375, "$\\Delta \\pi(\\cdot)$": -2.09808349609375e-05, "$\\Delta \\mathcal{J}(\\cdot)$": -4.76837158203125e-07, "$\\log(p(\\hat{y}_{n+1}|x_{n+1}, D))$": -12.375020980834961, "$p(\\hat{y}_{n+1}|x_{n+1}, D)$": 4.222762527206214e-06}, {"$\\tilde{\\theta}$": 4.999301910400391, "$\\hat{\\theta}$": 4.99929666519165, "$\\tilde{\\ell}(\\cdot)$": -1418335.25, "$\\hat{\\ell}(\\cdot)$": -1418321.875, "$\\tilde{\\pi}(\\cdot)$": -8.916146278381348, "$\\hat{\\pi}(\\cdot)$": -8.916125297546387, "$\\tilde{\\mathcal{J}}(\\cdot)$": 6.9077558517456055, "$\\hat{\\mathcal{J}}(\\cdot)$": 6.907755374908447, "$\\Delta \\ell(\\cdot)$": -13.375, "$\\Delta \\pi(\\cdot)$": -2.09808349609375e-05, "$\\Delta \\mathcal{J}(\\cdot)$": -4.76837158203125e-07, "$\\log(p(\\hat{y}_{n+1}|x_{n+1}, D))$": -13.375020980834961, "$p(\\hat{y}_{n+1}|x_{n+1}, D)$": 1.5534675412709475e-06}]